odoo/addons/endpoint_jsonifier/README.rst
odoo/addons/endpoint_jsonifier/__init__.py
odoo/addons/endpoint_jsonifier/__manifest__.py
odoo/addons/endpoint_jsonifier/i18n/endpoint_jsonifier.pot
odoo/addons/endpoint_jsonifier/models/__init__.py
odoo/addons/endpoint_jsonifier/models/endpoint_mixin.py
odoo/addons/endpoint_jsonifier/readme/CONTRIBUTORS.rst
odoo/addons/endpoint_jsonifier/readme/DESCRIPTION.rst
odoo/addons/endpoint_jsonifier/readme/USAGE.rst
odoo/addons/endpoint_jsonifier/static/description/icon.png
odoo/addons/endpoint_jsonifier/static/description/index.html
odoo/addons/endpoint_jsonifier/views/endpoint_endpoint.xml
odoo14_addon_endpoint_jsonifier-14.0.1.1.0.dist-info/METADATA
odoo14_addon_endpoint_jsonifier-14.0.1.1.0.dist-info/WHEEL
odoo14_addon_endpoint_jsonifier-14.0.1.1.0.dist-info/top_level.txt
odoo14_addon_endpoint_jsonifier-14.0.1.1.0.dist-info/RECORD
