Metadata-Version: 2.1
Name: odoo14-addon-endpoint_jsonifier
Version: 14.0.1.1.0
Summary: Allow to configure jsonifier parsers on endpoints
Home-page: https://github.com/OCA/web-api
Author: Camptocamp, Odoo Community Association (OCA)
Author-email: support@odoo-community.org
License: LGPL-3
Classifier: Programming Language :: Python
Classifier: Framework :: Odoo
Classifier: Framework :: Odoo :: 14.0
Classifier: License :: OSI Approved :: GNU Lesser General Public License v3 (LGPLv3)
Requires-Python: >=3.6
Requires-Dist: odoo14-addon-endpoint
Requires-Dist: odoo14-addon-jsonifier
Requires-Dist: odoo <14.1dev,>=14.0a
